listenbrainz_export/__init__.py
listenbrainz_export/__main__.py
listenbrainz_export/export.py
listenbrainz_export/parse.py
listenbrainz_export/py.typed
listenbrainz_export-0.2.2.dist-info/licenses/LICENSE
listenbrainz_export-0.2.2.dist-info/METADATA
listenbrainz_export-0.2.2.dist-info/WHEEL
listenbrainz_export-0.2.2.dist-info/entry_points.txt
listenbrainz_export-0.2.2.dist-info/top_level.txt
listenbrainz_export-0.2.2.dist-info/RECORD
