Metadata-Version: 2.4
Name: listenbrainz_export
Version: 0.2.2
Summary: Export your scrobbling history from ListenBrainz
Author: purarue
License-Expression: MIT
Project-URL: Homepage, https://github.com/purarue/listenbrainz_export
Keywords: music,scrobble,data
Classifier: Programming Language :: Python :: 3
Classifier: Programming Language :: Python :: 3 :: Only
Classifier: Programming Language :: Python :: 3.10
Classifier: Programming Language :: Python :: 3.11
Classifier: Programming Language :: Python :: 3.12
Classifier: Programming Language :: Python :: 3.13
Requires-Python: >=3.10
License-File: LICENSE
Requires-Dist: click>=8.0
Requires-Dist: logzero
Requires-Dist: requests
Provides-Extra: testing
Requires-Dist: flake8; extra == "testing"
Requires-Dist: mypy; extra == "testing"
Dynamic: license-file
